zooper_client/__init__.py
zooper_client/indeks.py
zooper_client-0.1.7.dist-info/METADATA
zooper_client-0.1.7.dist-info/WHEEL
zooper_client-0.1.7.dist-info/top_level.txt
zooper_client-0.1.7.dist-info/RECORD
