Metadata-Version: 2.1
Name: zooper-client
Version: 0.1.7
Summary: This package contains zooper client
Home-page: https://www.zooper.com
Author: Zooper
Author-email: hi@zooper.com
License: Apache License, Version 2.0
Keywords: zooper client
Platform: UNKNOWN
Classifier: Development Status :: 3 - Alpha
Classifier: Intended Audience :: Developers
Classifier: Natural Language :: English
Classifier: Operating System :: POSIX :: Linux
Classifier: Programming Language :: Python :: 3.6
Classifier: License :: OSI Approved :: Apache Software License
Requires-Dist: urllib3 (<1.25.0)
Requires-Dist: requests (==2.22.0)
Requires-Dist: requests-oauthlib (==1.3.0)
